flytekitplugins_omegaconf-1.16.12-py3.14-nspkg.pth
flytekitplugins/omegaconf/__init__.py
flytekitplugins/omegaconf/config.py
flytekitplugins/omegaconf/dictconfig_transformer.py
flytekitplugins/omegaconf/listconfig_transformer.py
flytekitplugins/omegaconf/type_information.py
flytekitplugins_omegaconf-1.16.12.dist-info/METADATA
flytekitplugins_omegaconf-1.16.12.dist-info/WHEEL
flytekitplugins_omegaconf-1.16.12.dist-info/entry_points.txt
flytekitplugins_omegaconf-1.16.12.dist-info/namespace_packages.txt
flytekitplugins_omegaconf-1.16.12.dist-info/top_level.txt
flytekitplugins_omegaconf-1.16.12.dist-info/RECORD
